fastramqpi/__init__.py
fastramqpi/app.py
fastramqpi/ariadne.py
fastramqpi/autogenerated_graphql_client/__init__.py
fastramqpi/autogenerated_graphql_client/_testing__create_employee.py
fastramqpi/autogenerated_graphql_client/_testing__get_employee.py
fastramqpi/autogenerated_graphql_client/_testing__send_event.py
fastramqpi/autogenerated_graphql_client/acknowledge_event.py
fastramqpi/autogenerated_graphql_client/async_base_client.py
fastramqpi/autogenerated_graphql_client/base_model.py
fastramqpi/autogenerated_graphql_client/client.py
fastramqpi/autogenerated_graphql_client/declare_event_listener.py
fastramqpi/autogenerated_graphql_client/declare_event_namespace.py
fastramqpi/autogenerated_graphql_client/enums.py
fastramqpi/autogenerated_graphql_client/exceptions.py
fastramqpi/autogenerated_graphql_client/fetch_event.py
fastramqpi/autogenerated_graphql_client/input_types.py
fastramqpi/autogenerated_graphql_client/scalars.py
fastramqpi/config.py
fastramqpi/context.py
fastramqpi/database.py
fastramqpi/depends.py
fastramqpi/events.py
fastramqpi/logging.py
fastramqpi/main.py
fastramqpi/metrics.py
fastramqpi/middleware.py
fastramqpi/os2mo_dar_client/__init__.py
fastramqpi/os2mo_dar_client/cli.py
fastramqpi/os2mo_dar_client/dar_client.py
fastramqpi/os2mo_dar_client/py.typed
fastramqpi/py.typed
fastramqpi/pytest_plugin.py
fastramqpi/pytest_util.py
fastramqpi/ra_utils/__init__.py
fastramqpi/ra_utils/apply.py
fastramqpi/ra_utils/async_to_sync.py
fastramqpi/ra_utils/asyncio_utils.py
fastramqpi/ra_utils/attrdict.py
fastramqpi/ra_utils/catchtime.py
fastramqpi/ra_utils/deprecation.py
fastramqpi/ra_utils/dict_map.py
fastramqpi/ra_utils/ensure_hashable.py
fastramqpi/ra_utils/ensure_single_run.py
fastramqpi/ra_utils/generate_uuid.py
fastramqpi/ra_utils/headers.py
fastramqpi/ra_utils/jinja_filter.py
fastramqpi/ra_utils/job_settings.py
fastramqpi/ra_utils/lazy_dict.py
fastramqpi/ra_utils/load_settings.py
fastramqpi/ra_utils/multiple_replace.py
fastramqpi-14.2.1.dist-info/METADATA
fastramqpi-14.2.1.dist-info/WHEEL
fastramqpi-14.2.1.dist-info/entry_points.txt
fastramqpi-14.2.1.dist-info/licenses/LICENSE
fastramqpi-14.2.1.dist-info/licenses/LICENSES/MPL-2.0.txt
fastramqpi-14.2.1.dist-info/RECORD
