Metadata-Version: 2.4
Name: FastRAMQPI
Version: 14.2.1
Summary: Rammearkitektur integrations framework
License: MPL-2.0
License-File: LICENSE
License-File: LICENSES/MPL-2.0.txt
Keywords: os2mo
Author: Magenta ApS
Author-email: info@magenta.dk
Requires-Python: >=3.11,<4.0
Classifier: License :: OSI Approved
Classifier: Programming Language :: Python :: 3
Classifier: Programming Language :: Python :: 3.11
Classifier: Programming Language :: Python :: 3.12
Classifier: Programming Language :: Python :: 3.13
Classifier: Programming Language :: Python :: 3.14
Requires-Dist: Authlib (>=1,<2)
Requires-Dist: Jinja2 (>=3,<4)
Requires-Dist: aio-pika (>=9,<10)
Requires-Dist: aiohttp (>=3,<4)
Requires-Dist: aiormq (>=6,<7)
Requires-Dist: anyio (>=3,<5)
Requires-Dist: ariadne-codegen (>=0.7,<0.8)
Requires-Dist: click (>=8,<9)
Requires-Dist: debugpy (>=1,<2)
Requires-Dist: fastapi (>=0.115,<0.116)
Requires-Dist: frozendict (>=2,<3)
Requires-Dist: gql (>=3,<4)
Requires-Dist: httpx (>=0.27,<0.29)
Requires-Dist: hypothesis (>=6,<7)
Requires-Dist: more-itertools (>=9,<11)
Requires-Dist: prometheus-client (>=0.20,<0.22)
Requires-Dist: prometheus-fastapi-instrumentator (>=7,<8)
Requires-Dist: psycopg (>=3,<4)
Requires-Dist: pydantic (>=1,<2)
Requires-Dist: pytest (>=8,<9)
Requires-Dist: requests (>=2,<3)
Requires-Dist: respx (>=0.21,<0.23)
Requires-Dist: sentry-sdk (>=2.47.0,<3.0.0)
Requires-Dist: sqlalchemy (>=2,<3)
Requires-Dist: starlette (>=0.41,<0.42)
Requires-Dist: structlog (>=24,<26)
Requires-Dist: tenacity (>=8,<10)
Requires-Dist: tqdm (>=4,<5)
Requires-Dist: uvicorn (>=0.34,<0.35)
Requires-Dist: websockets (>=13,<14)
Project-URL: Homepage, https://magenta.dk/
Project-URL: Repository, https://git.magenta.dk/rammearkitektur/FastRAMQPI
